{
  "id": "6d51232c-a86c-4543-aa33-e79dfd1b7e99",
  "prevId": "00000000-0000-0000-0000-000000000000",
  "version": "7",
  "dialect": "postgresql",
  "tables": {
    "public.comments": {
      "name": "comments",
      "schema": "",
      "columns": {
        "id": {
          "name": "id",
          "type": "integer",
          "primaryKey": true,
          "notNull": true,
          "identity": {
            "type": "always",
            "name": "comments_id_seq",
            "schema": "public",
            "increment": "1",
            "startWith": "1",
            "minValue": "1",
            "maxValue": "2147483647",
            "cache": "1",
            "cycle": false
          }
        },
        "content": {
          "name": "content",
          "type": "text",
          "primaryKey": false,
          "notNull": false
        },
        "taskId": {
          "name": "taskId",
          "type": "integer",
          "primaryKey": false,
          "notNull": true
        },
        "authorId": {
          "name": "authorId",
          "type": "integer",
          "primaryKey": false,
          "notNull": true
        },
        "created_at": {
          "name": "created_at",
          "type": "timestamp",
          "primaryKey": false,
          "notNull": true,
          "default": "now()"
        },
        "updated_at": {
          "name": "updated_at",
          "type": "timestamp",
          "primaryKey": false,
          "notNull": true,
          "default": "now()"
        },
        "isArchived": {
          "name": "isArchived",
          "type": "boolean",
          "primaryKey": false,
          "notNull": true,
          "default": false
        },
        "archivedAt": {
          "name": "archivedAt",
          "type": "timestamp",
          "primaryKey": false,
          "notNull": false
        }
      },
      "indexes": {},
      "foreignKeys": {
        "comments_taskId_tasks_id_fk": {
          "name": "comments_taskId_tasks_id_fk",
          "tableFrom": "comments",
          "tableTo": "tasks",
          "columnsFrom": [
            "taskId"
          ],
          "columnsTo": [
            "id"
          ],
          "onDelete": "no action",
          "onUpdate": "no action"
        },
        "comments_authorId_users_id_fk": {
          "name": "comments_authorId_users_id_fk",
          "tableFrom": "comments",
          "tableTo": "users",
          "columnsFrom": [
            "authorId"
          ],
          "columnsTo": [
            "id"
          ],
          "onDelete": "no action",
          "onUpdate": "no action"
        }
      },
      "compositePrimaryKeys": {},
      "uniqueConstraints": {},
      "policies": {},
      "checkConstraints": {},
      "isRLSEnabled": false
    },
    "public.lists": {
      "name": "lists",
      "schema": "",
      "columns": {
        "id": {
          "name": "id",
          "type": "integer",
          "primaryKey": true,
          "notNull": true,
          "identity": {
            "type": "always",
            "name": "lists_id_seq",
            "schema": "public",
            "increment": "1",
            "startWith": "1",
            "minValue": "1",
            "maxValue": "2147483647",
            "cache": "1",
            "cycle": false
          }
        },
        "name": {
          "name": "name",
          "type": "varchar",
          "primaryKey": false,
          "notNull": true
        },
        "projectId": {
          "name": "projectId",
          "type": "integer",
          "primaryKey": false,
          "notNull": true
        },
        "position": {
          "name": "position",
          "type": "integer",
          "primaryKey": false,
          "notNull": true
        },
        "created_at": {
          "name": "created_at",
          "type": "timestamp",
          "primaryKey": false,
          "notNull": true,
          "default": "now()"
        },
        "updated_at": {
          "name": "updated_at",
          "type": "timestamp",
          "primaryKey": false,
          "notNull": true,
          "default": "now()"
        },
        "isArchived": {
          "name": "isArchived",
          "type": "boolean",
          "primaryKey": false,
          "notNull": true,
          "default": false
        },
        "archivedAt": {
          "name": "archivedAt",
          "type": "timestamp",
          "primaryKey": false,
          "notNull": false
        }
      },
      "indexes": {},
      "foreignKeys": {
        "lists_projectId_projects_id_fk": {
          "name": "lists_projectId_projects_id_fk",
          "tableFrom": "lists",
          "tableTo": "projects",
          "columnsFrom": [
            "projectId"
          ],
          "columnsTo": [
            "id"
          ],
          "onDelete": "no action",
          "onUpdate": "no action"
        }
      },
      "compositePrimaryKeys": {},
      "uniqueConstraints": {},
      "policies": {},
      "checkConstraints": {},
      "isRLSEnabled": false
    },
    "public.projects": {
      "name": "projects",
      "schema": "",
      "columns": {
        "id": {
          "name": "id",
          "type": "integer",
          "primaryKey": true,
          "notNull": true,
          "identity": {
            "type": "always",
            "name": "projects_id_seq",
            "schema": "public",
            "increment": "1",
            "startWith": "1",
            "minValue": "1",
            "maxValue": "2147483647",
            "cache": "1",
            "cycle": false
          }
        },
        "name": {
          "name": "name",
          "type": "varchar",
          "primaryKey": false,
          "notNull": true
        },
        "description": {
          "name": "description",
          "type": "text",
          "primaryKey": false,
          "notNull": false
        },
        "status": {
          "name": "status",
          "type": "status",
          "typeSchema": "public",
          "primaryKey": false,
          "notNull": true,
          "default": "'Planning'"
        },
        "ownerId": {
          "name": "ownerId",
          "type": "integer",
          "primaryKey": false,
          "notNull": true
        },
        "teamId": {
          "name": "teamId",
          "type": "integer",
          "primaryKey": false,
          "notNull": true
        },
        "dueDate": {
          "name": "dueDate",
          "type": "timestamp",
          "primaryKey": false,
          "notNull": false
        },
        "created_at": {
          "name": "created_at",
          "type": "timestamp",
          "primaryKey": false,
          "notNull": true,
          "default": "now()"
        },
        "updated_at": {
          "name": "updated_at",
          "type": "timestamp",
          "primaryKey": false,
          "notNull": true,
          "default": "now()"
        },
        "isArchived": {
          "name": "isArchived",
          "type": "boolean",
          "primaryKey": false,
          "notNull": true,
          "default": false
        },
        "archivedAt": {
          "name": "archivedAt",
          "type": "timestamp",
          "primaryKey": false,
          "notNull": false
        }
      },
      "indexes": {},
      "foreignKeys": {
        "projects_ownerId_users_id_fk": {
          "name": "projects_ownerId_users_id_fk",
          "tableFrom": "projects",
          "tableTo": "users",
          "columnsFrom": [
            "ownerId"
          ],
          "columnsTo": [
            "id"
          ],
          "onDelete": "no action",
          "onUpdate": "no action"
        },
        "projects_teamId_teams_id_fk": {
          "name": "projects_teamId_teams_id_fk",
          "tableFrom": "projects",
          "tableTo": "teams",
          "columnsFrom": [
            "teamId"
          ],
          "columnsTo": [
            "id"
          ],
          "onDelete": "no action",
          "onUpdate": "no action"
        }
      },
      "compositePrimaryKeys": {},
      "uniqueConstraints": {},
      "policies": {},
      "checkConstraints": {},
      "isRLSEnabled": false
    },
    "public.roles": {
      "name": "roles",
      "schema": "",
      "columns": {
        "id": {
          "name": "id",
          "type": "integer",
          "primaryKey": true,
          "notNull": true,
          "identity": {
            "type": "always",
            "name": "roles_id_seq",
            "schema": "public",
            "increment": "1",
            "startWith": "1",
            "minValue": "1",
            "maxValue": "2147483647",
            "cache": "1",
            "cycle": false
          }
        },
        "role_name": {
          "name": "role_name",
          "type": "role_name",
          "typeSchema": "public",
          "primaryKey": false,
          "notNull": true,
          "default": "'No Role Yet'"
        }
      },
      "indexes": {},
      "foreignKeys": {},
      "compositePrimaryKeys": {},
      "uniqueConstraints": {
        "roles_role_name_unique": {
          "name": "roles_role_name_unique",
          "nullsNotDistinct": false,
          "columns": [
            "role_name"
          ]
        }
      },
      "policies": {},
      "checkConstraints": {},
      "isRLSEnabled": false
    },
    "public.task_assignees": {
      "name": "task_assignees",
      "schema": "",
      "columns": {
        "task_id": {
          "name": "task_id",
          "type": "integer",
          "primaryKey": false,
          "notNull": true
        },
        "user_id": {
          "name": "user_id",
          "type": "integer",
          "primaryKey": false,
          "notNull": true
        },
        "isTaskOwner": {
          "name": "isTaskOwner",
          "type": "boolean",
          "primaryKey": false,
          "notNull": true,
          "default": false
        },
        "created_at": {
          "name": "created_at",
          "type": "timestamp",
          "primaryKey": false,
          "notNull": true,
          "default": "now()"
        },
        "updated_at": {
          "name": "updated_at",
          "type": "timestamp",
          "primaryKey": false,
          "notNull": true,
          "default": "now()"
        },
        "isArchived": {
          "name": "isArchived",
          "type": "boolean",
          "primaryKey": false,
          "notNull": true,
          "default": false
        },
        "archived_at": {
          "name": "archived_at",
          "type": "timestamp",
          "primaryKey": false,
          "notNull": false
        }
      },
      "indexes": {},
      "foreignKeys": {
        "task_assignees_task_id_tasks_id_fk": {
          "name": "task_assignees_task_id_tasks_id_fk",
          "tableFrom": "task_assignees",
          "tableTo": "tasks",
          "columnsFrom": [
            "task_id"
          ],
          "columnsTo": [
            "id"
          ],
          "onDelete": "no action",
          "onUpdate": "no action"
        },
        "task_assignees_user_id_users_id_fk": {
          "name": "task_assignees_user_id_users_id_fk",
          "tableFrom": "task_assignees",
          "tableTo": "users",
          "columnsFrom": [
            "user_id"
          ],
          "columnsTo": [
            "id"
          ],
          "onDelete": "no action",
          "onUpdate": "no action"
        }
      },
      "compositePrimaryKeys": {
        "task_assignees_task_id_user_id_pk": {
          "name": "task_assignees_task_id_user_id_pk",
          "columns": [
            "task_id",
            "user_id"
          ]
        }
      },
      "uniqueConstraints": {},
      "policies": {},
      "checkConstraints": {},
      "isRLSEnabled": false
    },
    "public.tasks": {
      "name": "tasks",
      "schema": "",
      "columns": {
        "id": {
          "name": "id",
          "type": "integer",
          "primaryKey": true,
          "notNull": true,
          "identity": {
            "type": "always",
            "name": "tasks_id_seq",
            "schema": "public",
            "increment": "1",
            "startWith": "1",
            "minValue": "1",
            "maxValue": "2147483647",
            "cache": "1",
            "cycle": false
          }
        },
        "title": {
          "name": "title",
          "type": "varchar",
          "primaryKey": false,
          "notNull": true
        },
        "description": {
          "name": "description",
          "type": "text",
          "primaryKey": false,
          "notNull": false
        },
        "listId": {
          "name": "listId",
          "type": "integer",
          "primaryKey": false,
          "notNull": true
        },
        "priority": {
          "name": "priority",
          "type": "priority",
          "typeSchema": "public",
          "primaryKey": false,
          "notNull": true,
          "default": "'unselected'"
        },
        "labels": {
          "name": "labels",
          "type": "text[]",
          "primaryKey": false,
          "notNull": false
        },
        "dueDate": {
          "name": "dueDate",
          "type": "timestamp",
          "primaryKey": false,
          "notNull": false
        },
        "position": {
          "name": "position",
          "type": "integer",
          "primaryKey": false,
          "notNull": true
        },
        "created_at": {
          "name": "created_at",
          "type": "timestamp",
          "primaryKey": false,
          "notNull": true,
          "default": "now()"
        },
        "updated_at": {
          "name": "updated_at",
          "type": "timestamp",
          "primaryKey": false,
          "notNull": true,
          "default": "now()"
        },
        "isArchived": {
          "name": "isArchived",
          "type": "boolean",
          "primaryKey": false,
          "notNull": true,
          "default": false
        },
        "archivedAt": {
          "name": "archivedAt",
          "type": "timestamp",
          "primaryKey": false,
          "notNull": false
        }
      },
      "indexes": {},
      "foreignKeys": {
        "tasks_listId_lists_id_fk": {
          "name": "tasks_listId_lists_id_fk",
          "tableFrom": "tasks",
          "tableTo": "lists",
          "columnsFrom": [
            "listId"
          ],
          "columnsTo": [
            "id"
          ],
          "onDelete": "no action",
          "onUpdate": "no action"
        }
      },
      "compositePrimaryKeys": {},
      "uniqueConstraints": {},
      "policies": {},
      "checkConstraints": {},
      "isRLSEnabled": false
    },
    "public.team_members": {
      "name": "team_members",
      "schema": "",
      "columns": {
        "team_id": {
          "name": "team_id",
          "type": "integer",
          "primaryKey": false,
          "notNull": true
        },
        "user_id": {
          "name": "user_id",
          "type": "integer",
          "primaryKey": false,
          "notNull": true
        },
        "role": {
          "name": "role",
          "type": "integer",
          "primaryKey": false,
          "notNull": true,
          "default": 1
        },
        "isCreator": {
          "name": "isCreator",
          "type": "boolean",
          "primaryKey": false,
          "notNull": true,
          "default": false
        },
        "created_at": {
          "name": "created_at",
          "type": "timestamp",
          "primaryKey": false,
          "notNull": true,
          "default": "now()"
        },
        "updated_at": {
          "name": "updated_at",
          "type": "timestamp",
          "primaryKey": false,
          "notNull": true,
          "default": "now()"
        },
        "isArchived": {
          "name": "isArchived",
          "type": "boolean",
          "primaryKey": false,
          "notNull": true,
          "default": false
        },
        "archived_at": {
          "name": "archived_at",
          "type": "timestamp",
          "primaryKey": false,
          "notNull": false
        }
      },
      "indexes": {},
      "foreignKeys": {
        "team_members_team_id_teams_id_fk": {
          "name": "team_members_team_id_teams_id_fk",
          "tableFrom": "team_members",
          "tableTo": "teams",
          "columnsFrom": [
            "team_id"
          ],
          "columnsTo": [
            "id"
          ],
          "onDelete": "no action",
          "onUpdate": "no action"
        },
        "team_members_user_id_users_id_fk": {
          "name": "team_members_user_id_users_id_fk",
          "tableFrom": "team_members",
          "tableTo": "users",
          "columnsFrom": [
            "user_id"
          ],
          "columnsTo": [
            "id"
          ],
          "onDelete": "no action",
          "onUpdate": "no action"
        },
        "team_members_role_roles_id_fk": {
          "name": "team_members_role_roles_id_fk",
          "tableFrom": "team_members",
          "tableTo": "roles",
          "columnsFrom": [
            "role"
          ],
          "columnsTo": [
            "id"
          ],
          "onDelete": "no action",
          "onUpdate": "no action"
        }
      },
      "compositePrimaryKeys": {
        "team_members_team_id_user_id_pk": {
          "name": "team_members_team_id_user_id_pk",
          "columns": [
            "team_id",
            "user_id"
          ]
        }
      },
      "uniqueConstraints": {},
      "policies": {},
      "checkConstraints": {},
      "isRLSEnabled": false
    },
    "public.teams": {
      "name": "teams",
      "schema": "",
      "columns": {
        "id": {
          "name": "id",
          "type": "integer",
          "primaryKey": true,
          "notNull": true,
          "identity": {
            "type": "always",
            "name": "teams_id_seq",
            "schema": "public",
            "increment": "1",
            "startWith": "1",
            "minValue": "1",
            "maxValue": "2147483647",
            "cache": "1",
            "cycle": false
          }
        },
        "teamName": {
          "name": "teamName",
          "type": "varchar",
          "primaryKey": false,
          "notNull": true
        },
        "created_at": {
          "name": "created_at",
          "type": "timestamp",
          "primaryKey": false,
          "notNull": true,
          "default": "now()"
        },
        "updated_at": {
          "name": "updated_at",
          "type": "timestamp",
          "primaryKey": false,
          "notNull": true,
          "default": "now()"
        },
        "isArchived": {
          "name": "isArchived",
          "type": "boolean",
          "primaryKey": false,
          "notNull": true,
          "default": false
        },
        "archivedAt": {
          "name": "archivedAt",
          "type": "timestamp",
          "primaryKey": false,
          "notNull": false
        }
      },
      "indexes": {},
      "foreignKeys": {},
      "compositePrimaryKeys": {},
      "uniqueConstraints": {
        "teams_teamName_unique": {
          "name": "teams_teamName_unique",
          "nullsNotDistinct": false,
          "columns": [
            "teamName"
          ]
        }
      },
      "policies": {},
      "checkConstraints": {},
      "isRLSEnabled": false
    },
    "public.users": {
      "name": "users",
      "schema": "",
      "columns": {
        "id": {
          "name": "id",
          "type": "integer",
          "primaryKey": true,
          "notNull": true,
          "identity": {
            "type": "always",
            "name": "users_id_seq",
            "schema": "public",
            "increment": "1",
            "startWith": "1",
            "minValue": "1",
            "maxValue": "2147483647",
            "cache": "1",
            "cycle": false
          }
        },
        "clerk_id": {
          "name": "clerk_id",
          "type": "varchar",
          "primaryKey": false,
          "notNull": true
        },
        "email": {
          "name": "email",
          "type": "varchar",
          "primaryKey": false,
          "notNull": true
        },
        "name": {
          "name": "name",
          "type": "varchar",
          "primaryKey": false,
          "notNull": true
        },
        "image_url": {
          "name": "image_url",
          "type": "varchar",
          "primaryKey": false,
          "notNull": true
        },
        "created_at": {
          "name": "created_at",
          "type": "timestamp",
          "primaryKey": false,
          "notNull": true,
          "default": "now()"
        },
        "updated_at": {
          "name": "updated_at",
          "type": "timestamp",
          "primaryKey": false,
          "notNull": true,
          "default": "now()"
        },
        "isArchived": {
          "name": "isArchived",
          "type": "boolean",
          "primaryKey": false,
          "notNull": true,
          "default": false
        },
        "archivedAt": {
          "name": "archivedAt",
          "type": "timestamp",
          "primaryKey": false,
          "notNull": false
        }
      },
      "indexes": {},
      "foreignKeys": {},
      "compositePrimaryKeys": {},
      "uniqueConstraints": {
        "users_clerk_id_unique": {
          "name": "users_clerk_id_unique",
          "nullsNotDistinct": false,
          "columns": [
            "clerk_id"
          ]
        },
        "users_email_unique": {
          "name": "users_email_unique",
          "nullsNotDistinct": false,
          "columns": [
            "email"
          ]
        }
      },
      "policies": {},
      "checkConstraints": {},
      "isRLSEnabled": false
    }
  },
  "enums": {},
  "schemas": {},
  "sequences": {},
  "roles": {},
  "policies": {},
  "views": {},
  "_meta": {
    "columns": {},
    "schemas": {},
    "tables": {}
  }
}